<Complex name="Root" type="Eamon.Game.DataStorage.EffectDbTable, Eamon, Version=1.6.0.0, Culture=neutral, PublicKeyToken=null">
  <Properties>
    <Collection name="Records" type="Eamon.ThirdParty.BTree`1[[Eamon.Framework.IEffect, Eamon, Version=1.6.0.0, Culture=neutral, PublicKeyToken=null]], Eamon, Version=1.6.0.0, Culture=neutral, PublicKeyToken=null">
      <Properties>
        <Simple name="IsReadOnly" value="False" />
        <Simple name="AllowDuplicates" value="False" />
      </Properties>
      <Items>
        <Complex type="Eamon.Game.Effect, Eamon, Version=1.6.0.0, Culture=neutral, PublicKeyToken=null">
          <Properties>
            <Simple name="Uid" value="1" />
            <Simple name="IsUidRecycled" value="True" />
            <Simple name="Desc" value=" distance, you see majestic mountains rise, their peaks glistening white spires that jut upward from the low valley." />
          </Properties>
        </Complex>
        <Complex type="Eamon.Game.Effect, Eamon, Version=1.6.0.0, Culture=neutral, PublicKeyToken=null">
          <Properties>
            <Simple name="Uid" value="2" />
            <Simple name="IsUidRecycled" value="True" />
            <Simple name="Desc" value="The faded words on the signpost read:*003" />
          </Properties>
        </Complex>
        <Complex type="Eamon.Game.Effect, Eamon, Version=1.6.0.0, Culture=neutral, PublicKeyToken=null">
          <Properties>
            <Simple name="Uid" value="3" />
            <Simple name="IsUidRecycled" value="True" />
            <Simple name="Desc" value="             Aedrahr's Landing - North 40 leagues**004" />
          </Properties>
        </Complex>
        <Complex type="Eamon.Game.Effect, Eamon, Version=1.6.0.0, Culture=neutral, PublicKeyToken=null">
          <Properties>
            <Simple name="Uid" value="4" />
            <Simple name="IsUidRecycled" value="True" />
            <Simple name="Desc" value="                                           Wyveryn Mountains - South 60 leagues**005" />
          </Properties>
        </Complex>
        <Complex type="Eamon.Game.Effect, Eamon, Version=1.6.0.0, Culture=neutral, PublicKeyToken=null">
          <Properties>
            <Simple name="Uid" value="5" />
            <Simple name="IsUidRecycled" value="True" />
            <Simple name="Desc" value="                                           Glengarry Falls   - Northeast 17 leagues**006" />
          </Properties>
        </Complex>
        <Complex type="Eamon.Game.Effect, Eamon, Version=1.6.0.0, Culture=neutral, PublicKeyToken=null">
          <Properties>
            <Simple name="Uid" value="6" />
            <Simple name="IsUidRecycled" value="True" />
            <Simple name="Desc" value="                                       Geldhaven         - East 9 leagues" />
          </Properties>
        </Complex>
        <Complex type="Eamon.Game.Effect, Eamon, Version=1.6.0.0, Culture=neutral, PublicKeyToken=null">
          <Properties>
            <Simple name="Uid" value="7" />
            <Simple name="IsUidRecycled" value="True" />
            <Simple name="Desc" value="Rings of Zylo" />
          </Properties>
        </Complex>
        <Complex type="Eamon.Game.Effect, Eamon, Version=1.6.0.0, Culture=neutral, PublicKeyToken=null">
          <Properties>
            <Simple name="Uid" value="8" />
            <Simple name="IsUidRecycled" value="True" />
            <Simple name="Desc" value="It says, &quot;Johan's Backpack&quot;.  But not really clear on who Johan is or how you came to acquire his backpack!" />
          </Properties>
        </Complex>
        <Complex type="Eamon.Game.Effect, Eamon, Version=1.6.0.0, Culture=neutral, PublicKeyToken=null">
          <Properties>
            <Simple name="Uid" value="9" />
            <Simple name="IsUidRecycled" value="True" />
            <Simple name="Desc" value="loaves of bread" />
          </Properties>
        </Complex>
        <Complex type="Eamon.Game.Effect, Eamon, Version=1.6.0.0, Culture=neutral, PublicKeyToken=null">
          <Properties>
            <Simple name="Uid" value="10" />
            <Simple name="IsUidRecycled" value="True" />
            <Simple name="Desc" value="It says, &quot;AYERS FINE CHOCOLATES&quot;." />
          </Properties>
        </Complex>
        <Complex type="Eamon.Game.Effect, Eamon, Version=1.6.0.0, Culture=neutral, PublicKeyToken=null">
          <Properties>
            <Simple name="Uid" value="11" />
            <Simple name="IsUidRecycled" value="True" />
            <Simple name="Desc" value="The tome appears to be some sort of journal." />
          </Properties>
        </Complex>
        <Complex type="Eamon.Game.Effect, Eamon, Version=1.6.0.0, Culture=neutral, PublicKeyToken=null">
          <Properties>
            <Simple name="Uid" value="12" />
            <Simple name="IsUidRecycled" value="True" />
            <Simple name="Desc" value="The pages are filled with handwritten text detailing the adventures of someone named Johan.  The dated entries span several months." />
          </Properties>
        </Complex>
        <Complex type="Eamon.Game.Effect, Eamon, Version=1.6.0.0, Culture=neutral, PublicKeyToken=null">
          <Properties>
            <Simple name="Uid" value="13" />
            <Simple name="IsUidRecycled" value="True" />
            <Simple name="Desc" value="After a cursory viewing, most of the entries appear to be tall tales, or at least exaggerated for effect.  Regardless, its not clear at all why the tome was abandoned." />
          </Properties>
        </Complex>
        <Complex type="Eamon.Game.Effect, Eamon, Version=1.6.0.0, Culture=neutral, PublicKeyToken=null">
          <Properties>
            <Simple name="Uid" value="14" />
            <Simple name="IsUidRecycled" value="True" />
            <Simple name="Desc" value="The leaflet has a series of runes inscribed on it.*016" />
          </Properties>
        </Complex>
        <Complex type="Eamon.Game.Effect, Eamon, Version=1.6.0.0, Culture=neutral, PublicKeyToken=null">
          <Properties>
            <Simple name="Uid" value="15" />
            <Simple name="IsUidRecycled" value="True" />
            <Simple name="Desc" value="Little else can be gleaned based on your current level of knowledge.*017" />
          </Properties>
        </Complex>
        <Complex type="Eamon.Game.Effect, Eamon, Version=1.6.0.0, Culture=neutral, PublicKeyToken=null">
          <Properties>
            <Simple name="Uid" value="16" />
            <Simple name="IsUidRecycled" value="True" />
            <Simple name="Desc" value="It is in a strange pictographic language that you don't understand." />
          </Properties>
        </Complex>
        <Complex type="Eamon.Game.Effect, Eamon, Version=1.6.0.0, Culture=neutral, PublicKeyToken=null">
          <Properties>
            <Simple name="Uid" value="17" />
            <Simple name="IsUidRecycled" value="True" />
            <Simple name="Desc" value="At this point, you abandon your efforts to decipher the leaflet, intending to take it to Hokas for review at your earliest convenience." />
          </Properties>
        </Complex>
        <Complex type="Eamon.Game.Effect, Eamon, Version=1.6.0.0, Culture=neutral, PublicKeyToken=null">
          <Properties>
            <Simple name="Uid" value="18" />
            <Simple name="IsUidRecycled" value="True" />
            <Simple name="Desc" value="As you approach the chest, it suddenly comes alive and numerous tentacles burst out of it.  The chest starts to move awkwardly, propelled by small, stout tentacles underneath!*019" />
          </Properties>
        </Complex>
        <Complex type="Eamon.Game.Effect, Eamon, Version=1.6.0.0, Culture=neutral, PublicKeyToken=null">
          <Properties>
            <Simple name="Uid" value="19" />
            <Simple name="IsUidRecycled" value="True" />
            <Simple name="Desc" value="The creature's tentacles flail wildly as it searches for a victim to maul.*020" />
          </Properties>
        </Complex>
        <Complex type="Eamon.Game.Effect, Eamon, Version=1.6.0.0, Culture=neutral, PublicKeyToken=null">
          <Properties>
            <Simple name="Uid" value="20" />
            <Simple name="IsUidRecycled" value="True" />
            <Simple name="Desc" value="The chest monster advances toward you menacingly, somehow sensing your presence.  **021" />
          </Properties>
        </Complex>
        <Complex type="Eamon.Game.Effect, Eamon, Version=1.6.0.0, Culture=neutral, PublicKeyToken=null">
          <Properties>
            <Simple name="Uid" value="21" />
            <Simple name="IsUidRecycled" value="True" />
            <Simple name="Desc" value="At this point you fall into its grasp!!" />
          </Properties>
        </Complex>
        <Complex type="Eamon.Game.Effect, Eamon, Version=1.6.0.0, Culture=neutral, PublicKeyToken=null">
          <Properties>
            <Simple name="Uid" value="22" />
            <Simple name="IsUidRecycled" value="True" />
            <Simple name="Desc" value="It says, &quot;Abandon all hope, ye who enter here!!!&quot;" />
          </Properties>
        </Complex>
        <Complex type="Eamon.Game.Effect, Eamon, Version=1.6.0.0, Culture=neutral, PublicKeyToken=null">
          <Properties>
            <Simple name="Uid" value="23" />
            <Simple name="IsUidRecycled" value="True" />
            <Simple name="Desc" value="This is a sample adventure intoduction story.  Normally, you'll want to put something clever or exciting here, to intrigue the player or further describe the scenario.@@PB**024" />
          </Properties>
        </Complex>
        <Complex type="Eamon.Game.Effect, Eamon, Version=1.6.0.0, Culture=neutral, PublicKeyToken=null">
          <Properties>
            <Simple name="Uid" value="24" />
            <Simple name="IsUidRecycled" value="True" />
            <Simple name="Desc" value="But in the case of Test Adventure, please be aware this is a test adventure in the literal sense:  badly written, lacking any narrative and a jumble of far-too-many artifacts packed into far-too-few rooms.  It was **025" />
          </Properties>
        </Complex>
        <Complex type="Eamon.Game.Effect, Eamon, Version=1.6.0.0, Culture=neutral, PublicKeyToken=null">
          <Properties>
            <Simple name="Uid" value="25" />
            <Simple name="IsUidRecycled" value="True" />
            <Simple name="Desc" value="built in an ad-hoc manner to stress test various parts of Eamon CS during development.  As such, it is not really suitable for regular characters to adventure in.@@PB**026" />
          </Properties>
        </Complex>
        <Complex type="Eamon.Game.Effect, Eamon, Version=1.6.0.0, Culture=neutral, PublicKeyToken=null">
          <Properties>
            <Simple name="Uid" value="26" />
            <Simple name="IsUidRecycled" value="True" />
            <Simple name="Desc" value="It is included in the distribution because it exercises the game engine in a more rounded way than The Beginner's Cave.  Please feel free to look around!" />
          </Properties>
        </Complex>
        <Complex type="Eamon.Game.Effect, Eamon, Version=1.6.0.0, Culture=neutral, PublicKeyToken=null">
          <Properties>
            <Simple name="Uid" value="27" />
            <Simple name="IsUidRecycled" value="True" />
            <Simple name="Desc" value="unnatural and poses questions in your mind." />
          </Properties>
        </Complex>
      </Items>
    </Collection>
    <Collection name="FreeUids" type="System.Collections.Generic.List`1[[System.Int64, mscorlib, Version=4.0.0.0, Culture=neutral, PublicKeyToken=b77a5c561934e089]], mscorlib, Version=4.0.0.0, Culture=neutral, PublicKeyToken=b77a5c561934e089">
      <Properties>
        <Simple name="Capacity" value="4" />
      </Properties>
      <Items />
    </Collection>
    <Simple name="CurrUid" value="27" />
  </Properties>
</Complex>